devtools_shorthand_sql/__init__.py
devtools_shorthand_sql/cli.py
devtools_shorthand_sql/core.py
devtools_shorthand_sql/fields.py
devtools_shorthand_sql/parser.py
devtools_shorthand_sql/templates.py
devtools_shorthand_sql/utils.py
devtools_shorthand_sql-0.4.0.dist-info/AUTHORS.rst
devtools_shorthand_sql-0.4.0.dist-info/LICENSE
devtools_shorthand_sql-0.4.0.dist-info/METADATA
devtools_shorthand_sql-0.4.0.dist-info/WHEEL
devtools_shorthand_sql-0.4.0.dist-info/entry_points.txt
devtools_shorthand_sql-0.4.0.dist-info/top_level.txt
devtools_shorthand_sql-0.4.0.dist-info/RECORD
