Metadata-Version: 2.1
Name: devtools-shorthand-sql
Version: 0.4.0
Summary: Aid writing boilerplate SQL items from create tables, inserts and updates.
Home-page: https://github.com/HaeckelK/devtools_shorthand_sql
Author: Haeckel K
Author-email: haeckelk.github@gmail.com
License: MIT license
Keywords: devtools_shorthand_sql
Platform: UNKNOWN
Classifier: Development Status :: 2 - Pre-Alpha
Classifier: Intended Audience :: Developers
Classifier: License :: OSI Approved :: MIT License
Classifier: Natural Language :: English
Classifier: Programming Language :: Python :: 3
Classifier: Programming Language :: Python :: 3.6
Classifier: Programming Language :: Python :: 3.7
Classifier: Programming Language :: Python :: 3.8
Requires-Python: >=3.6
